README
setup.py
biwigpuprep/__init__.py
biwigpuprep.egg-info/PKG-INFO
biwigpuprep.egg-info/SOURCES.txt
biwigpuprep.egg-info/dependency_links.txt
biwigpuprep.egg-info/not-zip-safe
biwigpuprep.egg-info/top_level.txt