Metadata-Version: 1.0
Name: biwigpuprep
Version: 0.3
Summary:  Simple script for setting environment variables before using GPU cluster at CVL Lab ETH Zurich 
Home-page: https://github.com/metamercurial/biwi-gpu-prep
Author: Jonathan Gan
Author-email: jongan@student.ethz.ch
License: MIT
Platform: UNKNOWN
